template_python_cmd/__init__.py
template_python_cmd/cli.py
template_python_cmd/assets/example.txt
template_python_cmd-1.0.1.dist-info/LICENSE
template_python_cmd-1.0.1.dist-info/METADATA
template_python_cmd-1.0.1.dist-info/WHEEL
template_python_cmd-1.0.1.dist-info/entry_points.txt
template_python_cmd-1.0.1.dist-info/top_level.txt
template_python_cmd-1.0.1.dist-info/RECORD
