Metadata-Version: 2.1
Name: template-python-cmd
Version: 1.0.1
Summary: Cross platform(ish) productivity commands written in python.
Home-page: https://github.com/zackees/template-python-cmd
Maintainer: Zachary Vorhies
License: BSD 3-Clause License
Keywords: template-python-cmd
Classifier: Programming Language :: Python :: 3
Requires-Python: >=3.7
License-File: LICENSE
